pulsemeeter/__init__.py
pulsemeeter/__main__.py
pulsemeeter/config.json
pulsemeeter/settings.py
pulsemeeter/backends/__init__.py
pulsemeeter/backends/pulse.py
pulsemeeter/interface/__init__.py
pulsemeeter/interface/app_list_widget.py
pulsemeeter/interface/eq_popover.py
pulsemeeter/interface/groups_popover.py
pulsemeeter/interface/latency_popover.py
pulsemeeter/interface/main_window.py
pulsemeeter/interface/port_select_popover.py
pulsemeeter/interface/rnnoise_popover.py
pulsemeeter/interface/vumeter_widget.py
pulsemeeter/interface/layouts/default.glade
pulsemeeter/interface/layouts/tabbed.glade
pulsemeeter/socket/__init__.py
pulsemeeter/socket/client.py
pulsemeeter/socket/server.py
pulsemeeter-1.2.14.data/data/share/applications/pulsemeeter.desktop
pulsemeeter-1.2.14.data/data/share/icons/hicolor/128x128/apps/Pulsemeeter.png
pulsemeeter-1.2.14.data/data/share/icons/hicolor/16x16/apps/Pulsemeeter.png
pulsemeeter-1.2.14.data/data/share/icons/hicolor/192x192/apps/Pulsemeeter.png
pulsemeeter-1.2.14.data/data/share/icons/hicolor/22x22/apps/Pulsemeeter.png
pulsemeeter-1.2.14.data/data/share/icons/hicolor/24x24/apps/Pulsemeeter.png
pulsemeeter-1.2.14.data/data/share/icons/hicolor/32x32/apps/Pulsemeeter.png
pulsemeeter-1.2.14.data/data/share/icons/hicolor/48x48/apps/Pulsemeeter.png
pulsemeeter-1.2.14.data/data/share/icons/hicolor/64x64/apps/Pulsemeeter.png
pulsemeeter-1.2.14.data/data/share/icons/hicolor/8x8/apps/Pulsemeeter.png
pulsemeeter-1.2.14.data/data/share/icons/hicolor/96x96/apps/Pulsemeeter.png
pulsemeeter-1.2.14.data/data/share/licenses/pulsemeeter/LICENSE
pulsemeeter-1.2.14.data/scripts/pmctl
pulsemeeter-1.2.14.dist-info/LICENSE
pulsemeeter-1.2.14.dist-info/METADATA
pulsemeeter-1.2.14.dist-info/WHEEL
pulsemeeter-1.2.14.dist-info/entry_points.txt
pulsemeeter-1.2.14.dist-info/top_level.txt
pulsemeeter-1.2.14.dist-info/RECORD
