Metadata-Version: 2.1
Name: pulsemeeter
Version: 1.2.14
Summary: A pulseaudio audio routing application
Home-page: https://github.com/theRealCarneiro/pulsemeeter
Author: Gabriel Carneiro
Author-email: therealcarneiro@gmail.com
License: MIT
Platform: UNKNOWN
Classifier: Environment :: X11 Applications
Classifier: License :: OSI Approved :: MIT License
Requires-Python: >=3.5
Requires-Dist: setuptools
Requires-Dist: pulsectl
Requires-Dist: pygobject
